README.txt
bootstrap.py
buildout.cfg
setup.py
Products/__init__.py
Products.SimpleUserFolder.egg-info/PKG-INFO
Products.SimpleUserFolder.egg-info/SOURCES.txt
Products.SimpleUserFolder.egg-info/dependency_links.txt
Products.SimpleUserFolder.egg-info/not-zip-safe
Products.SimpleUserFolder.egg-info/requires.txt
Products.SimpleUserFolder.egg-info/top_level.txt
Products/SimpleUserFolder/SimpleUserFolder.py
Products/SimpleUserFolder/User.py
Products/SimpleUserFolder/__init__.py
Products/SimpleUserFolder/license.txt
Products/SimpleUserFolder/tests/__init__.py
Products/SimpleUserFolder/tests/addUser.pys
Products/SimpleUserFolder/tests/addUser.sql
Products/SimpleUserFolder/tests/base.py
Products/SimpleUserFolder/tests/createTables.sql
Products/SimpleUserFolder/tests/deleteUser.pys
Products/SimpleUserFolder/tests/deleteUser.sql
Products/SimpleUserFolder/tests/dummyUserSource.py
Products/SimpleUserFolder/tests/editUser.pys
Products/SimpleUserFolder/tests/editUser.sql
Products/SimpleUserFolder/tests/getUserDetails.pys
Products/SimpleUserFolder/tests/getUserDetails.sql
Products/SimpleUserFolder/tests/getUserIds.pys
Products/SimpleUserFolder/tests/getUserIds.sql
Products/SimpleUserFolder/tests/security.py
Products/SimpleUserFolder/tests/test_AcquireUsage.py
Products/SimpleUserFolder/tests/test_Broken.py
Products/SimpleUserFolder/tests/test_ContainedUsage.py
Products/SimpleUserFolder/tests/test_Creation.py
Products/SimpleUserFolder/tests/test_PythonScriptUsage.py
Products/SimpleUserFolder/tests/test_SQLUsage.py
Products/SimpleUserFolder/tests/test_SubclassUsage.py
Products/SimpleUserFolder/tests/test_Unconfigured.py
Products/SimpleUserFolder/tests/test_User.py
Products/SimpleUserFolder/www/suf.gif
docs/Makefile
docs/changes.txt
docs/conf.py
docs/description.txt
docs/development.txt
docs/index.txt
docs/installation.txt
docs/license.txt
docs/make.bat
docs/use.txt